axinite/__init__.py
axinite/body.py
axinite/functions.py
axinite/load.py
axinite/analysis/__init__.py
axinite/analysis/angles.py
axinite/analysis/approximate.py
axinite/analysis/collisions.py
axinite/analysis/energy.py
axinite/analysis/intercept.py
axinite/analysis/intersections.py
axinite/analysis/momentum.py
axinite/analysis/orbit.py
axinite/analysis/quaternions.py
axinite/analysis/raycasts.py
axinite/backends/euler.py
axinite/backends/rk2.py
axinite/backends/rk3.py
axinite/backends/rk4.py
axinite/backends/verlet.py
axinite/tools/__init__.py
axinite/tools/args.py
axinite/tools/body.py
axinite/tools/combine.py
axinite/tools/functions.py
axinite/tools/live.py
axinite/tools/load.py
axinite/tools/read.py
axinite/tools/run.py
axinite/tools/save.py
axinite/tools/show.py
axinite/tools/frontends/mpl.py
axinite/tools/frontends/plotly.py
axinite/tools/frontends/vpython.py
axinite/utils/__init__.py
axinite/utils/autopilots.py
axinite/utils/magnetic.py
axinite/utils/modifier.py
axinite/utils/normal.py
axinite-1.24.17.dist-info/LICENSE.md
axinite-1.24.17.dist-info/METADATA
axinite-1.24.17.dist-info/WHEEL
axinite-1.24.17.dist-info/top_level.txt
axinite-1.24.17.dist-info/RECORD
