Metadata-Version: 2.2
Name: axinite
Version: 1.24.17
Summary: A powerful open-source engine for advanced celestial mechanics.
Author-email: Jewels <jewels@jewels86.me>
Maintainer-email: Jewels <jewels@jewels86.me>
License: MIT License
Project-URL: Homepage, https://jewels86.me/solutions?s=axinite
Project-URL: Documentation, https://jewels86.gitbook.io/axinite
Project-URL: Repository, https://github.com/jewels86/axinite
Keywords: celestial-mechanics,orbital-dynamics,engine,astrodynamics
Classifier: Development Status :: 4 - Beta
License-File: LICENSE.md
Requires-Dist: numpy
Requires-Dist: numba
Requires-Dist: vpython
Requires-Dist: plotly
Requires-Dist: scipy
Requires-Dist: matplotlib
